redis_model_store/__init__.py
redis_model_store/serialize.py
redis_model_store/shard_manager.py
redis_model_store/store.py
redis_model_store/utils.py
redis_model_store-0.0.2.dist-info/LICENSE
redis_model_store-0.0.2.dist-info/METADATA
redis_model_store-0.0.2.dist-info/WHEEL
redis_model_store-0.0.2.dist-info/entry_points.txt
redis_model_store-0.0.2.dist-info/RECORD
