Metadata-Version: 2.1
Name: redis-model-store
Version: 0.0.2
Summary: Library to handle versioning and serialization of AI/ML models into Redis.
Home-page: https://github.com/redis-applied-ai/redis-model-store
License: MIT
Keywords: ai,redis,redis-client,model-store,mlops
Author: Tyler Hutcherson
Author-email: tyler.hutcherson@redis.com
Requires-Python: >=3.9,<3.14
Classifier: License :: OSI Approved :: MIT License
Classifier: Programming Language :: Python :: 3
Classifier: Programming Language :: Python :: 3.9
Classifier: Programming Language :: Python :: 3.10
Classifier: Programming Language :: Python :: 3.11
Classifier: Programming Language :: Python :: 3.12
Requires-Dist: pydantic (>=2.10.5,<3.0.0)
Requires-Dist: redisvl (>=0.6.0,<0.7.0)
Project-URL: Repository, https://github.com/redis-applied-ai/redis-model-store
